pyats/contrib/__init__.py
pyats/contrib/creators/__init__.py
pyats/contrib/creators/ansible.py
pyats/contrib/creators/creator.py
pyats/contrib/creators/file.py
pyats/contrib/creators/interactive.py
pyats/contrib/creators/netbox.py
pyats/contrib/creators/template.py
pyats/contrib/creators/topology.py
pyats/contrib/creators/yamltemplate.py
pyats/contrib/creators/libs/__init__.py
pyats/contrib/creators/libs/testbed_manager.py
pyats/contrib/creators/tests/__init__.py
pyats/contrib/creators/tests/test_ansible.py
pyats/contrib/creators/tests/test_creator.py
pyats/contrib/creators/tests/test_file.py
pyats/contrib/creators/tests/test_interactive.py
pyats/contrib/creators/tests/test_netbox.py
pyats/contrib/creators/tests/test_template.py
pyats/contrib/creators/tests/test_yamltemplate.py
pyats/contrib/creators/tests/netbox_mock_data/constants.py
pyats/contrib/plugins/__init__.py
pyats/contrib/plugins/topoup_plugin/__init__.py
pyats/contrib/plugins/topoup_plugin/topoup.py
pyats/contrib/plugins/webex_plugin/__init__.py
pyats/contrib/plugins/webex_plugin/webex.py
pyats/contrib/tests/creators/__init__.py
pyats/contrib/tests/creators/test_ansible.py
pyats/contrib/tests/creators/test_creator.py
pyats/contrib/tests/creators/test_file.py
pyats/contrib/tests/creators/test_interactive.py
pyats/contrib/tests/creators/test_netbox.py
pyats/contrib/tests/creators/test_template.py
pyats/contrib/tests/creators/test_yamltemplate.py
pyats/contrib/tests/creators/netbox_mock_data/constants.py
pyats.contrib-25.9.dist-info/LICENSE
pyats.contrib-25.9.dist-info/METADATA
pyats.contrib-25.9.dist-info/WHEEL
pyats.contrib-25.9.dist-info/entry_points.txt
pyats.contrib-25.9.dist-info/top_level.txt
pyats.contrib-25.9.dist-info/RECORD
