Metadata-Version: 2.1
Name: pyats.contrib
Version: 25.9
Summary: Open source package for pyATS framework extensions.
Home-page: https://developer.cisco.com/pyats/
Author: Cisco Systems Inc.
Author-email: pyats-support-ext@cisco.com
License: Apache 2.0
Keywords: genie pyats test automation open source contrib
Classifier: Development Status :: 6 - Mature
Classifier: Development Status :: 5 - Production/Stable
Classifier: Environment :: Console
Classifier: Intended Audience :: Developers
Classifier: Intended Audience :: Telecommunications Industry
Classifier: Intended Audience :: Information Technology
Classifier: Intended Audience :: System Administrators
Classifier: License :: OSI Approved :: Apache Software License
Classifier: Operating System :: MacOS
Classifier: Operating System :: POSIX :: Linux
Classifier: Programming Language :: Python :: 3.8
Classifier: Programming Language :: Python :: 3.7
Classifier: Programming Language :: Python :: 3.6
Classifier: Programming Language :: Python :: 3.5
Classifier: Programming Language :: Python :: 3 :: Only
Classifier: Programming Language :: Python :: Implementation :: CPython
Classifier: Topic :: Software Development :: Testing
Classifier: Topic :: Software Development :: Build Tools
Classifier: Topic :: Software Development :: Libraries
Classifier: Topic :: Software Development :: Libraries :: Python Modules
License-File: LICENSE
Requires-Dist: requests
Requires-Dist: requests-toolbelt
Requires-Dist: xlrd==1.2
Requires-Dist: xlwt
Requires-Dist: xlsxwriter
